RAM/ram.v
module ram
    (   input clk,       //clock
        input wr_en,         //write enable
        input resetRam,
        input [9:0] data_in,     //Input data.
        input [4:0] addr,   //address
        output [9:0] data_out //output data
    );

//memory declaration.
reg [9:0] ram[0:15];

always @(posedge clk) begin
    if (resetRam) begin
        for (integer i = 0; i < 16; i = i + 1) begin
            ram[i] <= {10{1'b0}};
        end
    end else if (wr_en) begin
        ram[addr] <= data_in;
    end
end

//always reading from the ram, irrespective of clock.
assign data_out = !wr_en ? ram[addr] : 'h0;

endmodule 

module ram_tb;

    // Inputs
    reg clk;
    reg wr_en;
    reg resetRam;
    wire [9:0] data_in;
    reg [4:0] addr;
    
    // Outputs
    wire [9:0] data_out;

    reg [9:0] tb_data;
    
    integer i;

   
    ram iram(.*);
    
    assign data_in = wr_en ? tb_data : 'h0 ;

    always
        #5 clk = ~clk;

    initial begin
        $monitor("addrs = %b resetRam=%b Write = %b  dataIn = %b dataOut = %b", addr,resetRam,wr_en,data_in,data_out);
        $dumpfile("ram_tb.vcd");
        $dumpvars(0,ram_tb);
        // Initialize Inputs
        clk <= 0;
        addr <= 0;
        wr_en <= 0;
        resetRam <= 0;
        tb_data <= 0;  
        #20;

        //Write all the locations of RAM  
        wr_en <= 1;
      for(i=1; i <= 16; i = i + 1) begin
            tb_data <= i;
            addr <= i-1;
            #10;
        end
        wr_en <= 0;

        //Read from  all the locations of RAM.
        for(i=1; i <= 16; i = i + 1) begin
            addr <= i-1;
            #10;
        end

        //resetRam
        resetRam <= 1;
        #10;
        resetRam <= 0;
        #10;

        //Read from  all the locations of RAM.
        for(i=1; i <= 16; i = i + 1) begin
            addr <= i-1;
            #10;
        end


        

    #100
    $finish;
    end
       
endmodule

//iverilog -o ram_tb.vpp ram.v
//vvp ram_tb.vpp

RAM/ram_tb.vcd
$date
	Fri Jul 15 07:39:03 2022
$end
$version
	Icarus Verilog
$end
$timescale
	1s
$end
$scope module ram_tb $end
$var wire 10 ! data_out [9:0] $end
$var wire 10 " data_in [9:0] $end
$var reg 5 # addr [4:0] $end
$var reg 1 $ clk $end
$var reg 1 % resetRam $end
$var reg 10 & tb_data [9:0] $end
$var reg 1 ' wr_en $end
$var integer 32 ( i [31:0] $end
$scope module iram $end
$var wire 5 ) addr [4:0] $end
$var wire 1 $ clk $end
$var wire 10 * data_in [9:0] $end
$var wire 1 % resetRam $end
$var wire 1 ' wr_en $end
$var wire 10 + data_out [9:0] $end
$scope begin $ivl_for_loop0 $end
$var integer 32 , i [31:0] $end
$upscope $end
$upscope $end
$upscope $end
$enddefinitions $end
#0
$dumpvars
bx ,
bx +
b0 *
b0 )
bx (
0'
b0 &
0%
0$
b0 #
b0 "
bx !
$end
#5
1$
#10
0$
#15
1$
#20
b1 "
b1 *
b0 !
b0 +
b1 &
1'
0$
b1 (
#25
1$
#30
b10 "
b10 *
b1 #
b1 )
b10 &
0$
b10 (
#35
1$
#40
b11 "
b11 *
b10 #
b10 )
b11 &
0$
b11 (
#45
1$
#50
b100 "
b100 *
b11 #
b11 )
b100 &
0$
b100 (
#55
1$
#60
b101 "
b101 *
b100 #
b100 )
b101 &
0$
b101 (
#65
1$
#70
b110 "
b110 *
b101 #
b101 )
b110 &
0$
b110 (
#75
1$
#80
b111 "
b111 *
b110 #
b110 )
b111 &
0$
b111 (
#85
1$
#90
b1000 "
b1000 *
b111 #
b111 )
b1000 &
0$
b1000 (
#95
1$
#100
b1001 "
b1001 *
b1000 #
b1000 )
b1001 &
0$
b1001 (
#105
1$
#110
b1010 "
b1010 *
b1001 #
b1001 )
b1010 &
0$
b1010 (
#115
1$
#120
b1011 "
b1011 *
b1010 #
b1010 )
b1011 &
0$
b1011 (
#125
1$
#130
b1100 "
b1100 *
b1011 #
b1011 )
b1100 &
0$
b1100 (
#135
1$
#140
b1101 "
b1101 *
b1100 #
b1100 )
b1101 &
0$
b1101 (
#145
1$
#150
b1110 "
b1110 *
b1101 #
b1101 )
b1110 &
0$
b1110 (
#155
1$
#160
b1111 "
b1111 *
b1110 #
b1110 )
b1111 &
0$
b1111 (
#165
1$
#170
b10000 "
b10000 *
b1111 #
b1111 )
b10000 &
0$
b10000 (
#175
1$
#180
b0 "
b0 *
b1 !
b1 +
b0 #
b0 )
0'
0$
b1 (
#185
1$
#190
b10 !
b10 +
b1 #
b1 )
0$
b10 (
#195
1$
#200
b11 !
b11 +
b10 #
b10 )
0$
b11 (
#205
1$
#210
b100 !
b100 +
b11 #
b11 )
0$
b100 (
#215
1$
#220
b101 !
b101 +
b100 #
b100 )
0$
b101 (
#225
1$
#230
b110 !
b110 +
b101 #
b101 )
0$
b110 (
#235
1$
#240
b111 !
b111 +
b110 #
b110 )
0$
b111 (
#245
1$
#250
b1000 !
b1000 +
b111 #
b111 )
0$
b1000 (
#255
1$
#260
b1001 !
b1001 +
b1000 #
b1000 )
0$
b1001 (
#265
1$
#270
b1010 !
b1010 +
b1001 #
b1001 )
0$
b1010 (
#275
1$
#280
b1011 !
b1011 +
b1010 #
b1010 )
0$
b1011 (
#285
1$
#290
b1100 !
b1100 +
b1011 #
b1011 )
0$
b1100 (
#295
1$
#300
b1101 !
b1101 +
b1100 #
b1100 )
0$
b1101 (
#305
1$
#310
b1110 !
b1110 +
b1101 #
b1101 )
0$
b1110 (
#315
1$
#320
b1111 !
b1111 +
b1110 #
b1110 )
0$
b1111 (
#325
1$
#330
b10000 !
b10000 +
b1111 #
b1111 )
0$
b10000 (
#335
1$
#340
1%
0$
b10001 (
#345
b0 !
b0 +
b10000 ,
1$
#350
0%
0$
#355
1$
#360
b0 #
b0 )
0$
b1 (
#365
1$
#370
b1 #
b1 )
0$
b10 (
#375
1$
#380
b10 #
b10 )
0$
b11 (
#385
1$
#390
b11 #
b11 )
0$
b100 (
#395
1$
#400
b100 #
b100 )
0$
b101 (
#405
1$
#410
b101 #
b101 )
0$
b110 (
#415
1$
#420
b110 #
b110 )
0$
b111 (
#425
1$
#430
b111 #
b111 )
0$
b1000 (
#435
1$
#440
b1000 #
b1000 )
0$
b1001 (
#445
1$
#450
b1001 #
b1001 )
0$
b1010 (
#455
1$
#460
b1010 #
b1010 )
0$
b1011 (
#465
1$
#470
b1011 #
b1011 )
0$
b1100 (
#475
1$
#480
b1100 #
b1100 )
0$
b1101 (
#485
1$
#490
b1101 #
b1101 )
0$
b1110 (
#495
1$
#500
b1110 #
b1110 )
0$
b1111 (
#505
1$
#510
b1111 #
b1111 )
0$
b10000 (
#515
1$
#520
0$
b10001 (
