Encoder/encoder16to4.v
module encoder16to4 (encoder_in,valid,encoder_out);

input [15:0]encoder_in;
output reg valid;
output reg [3:0] encoder_out;


// 0000 --- 0000
// 0001 --- 0001
always @(*) begin
    case(encoder_in)
         16'b0000000000000001 : begin
            valid = 1'b1;
            if (valid) begin
               encoder_out =4'b0000;
            end
         end  
         16'b0000000000000010 : begin
            valid = 1'b1;
            if (valid) begin
               encoder_out =4'b0001;
            end
         end 
         16'b0000000000000100 : begin
            valid = 1'b1;
            if (valid) begin
               encoder_out =4'b0010;
            end
         end 
         16'b0000000000001000 : begin
            valid = 1'b1;
            if (valid) begin
               encoder_out =4'b0011;
            end
         end 
         16'b0000000000010000 :begin
            valid = 1'b1;
            if (valid) begin
               encoder_out =4'b0100;
            end
         end 
         16'b0000000000100000 : begin
            valid = 1'b1;
            if (valid) begin
               encoder_out =4'b0101;
            end
         end 
         16'b0000000001000000 : begin
            valid = 1'b1;
            if (valid) begin
               encoder_out =4'b0110;
            end
         end 
         16'b0000000010000000 : begin
            valid = 1'b1;
            if (valid) begin
               encoder_out =4'b0111;
            end
         end 
         16'b0000000100000000 : begin
            valid = 1'b1;
            if (valid) begin
               encoder_out =4'b1000;
            end
         end 
         16'b0000001000000000 : begin
            valid = 1'b1;
            if (valid) begin
               encoder_out =4'b1001;
            end
         end 
         16'b0000010000000000 : begin
            valid = 1'b1;
            if (valid) begin
               encoder_out =4'b1010;
            end
         end 
         16'b0000100000000000 : begin
            valid = 1'b1;
            if (valid) begin
               encoder_out =4'b1011;
            end
         end 
         16'b0001000000000000 : begin
            valid = 1'b1;
            if (valid) begin
               encoder_out =4'b1100;
            end
         end 
         16'b0010000000000000 : begin
            valid = 1'b1;
            if (valid) begin
               encoder_out =4'b1101;
            end
         end 
         16'b0100000000000000 : begin
            valid = 1'b1;
            if (valid) begin
               encoder_out =4'b1110;
            end
         end 
         16'b1000000000000000 : begin
            valid = 1'b1;
            if (valid) begin
               encoder_out =4'b1111;
            end
         end 
         default: begin
            valid=1'b0;encoder_out =4'b0000;
         end 
         endcase
    end
endmodule

Encoder/encoder16to4_tb.v
`include "encoder16to4.v"

module encoder16to4_tb();

reg [15:0]encoder_in;
wire valid;
wire [3:0]encoder_out;

encoder16to4 iencoder16to4(encoder_in,valid,encoder_out);



initial begin
    $monitor("in=%b; valid=%b; out=%b", encoder_in, valid, encoder_out);
    $dumpfile("encoder16to4_tb.vcd");
    $dumpvars(0,encoder16to4_tb);
     
     encoder_in=16'b0000000000000000;#10; 
     encoder_in=16'b0000000000000001;#10;
     encoder_in=16'b0000000000000010;#10; 
     encoder_in=16'b0000000000000100;#10;  
     encoder_in=16'b0000000000001000;#10;
     encoder_in=16'b0000000000010000;#10; 
     encoder_in=16'b1000000000000000;#10;
     encoder_in=16'b1000010001000000;#10;
     encoder_in=16'b1000010001000100;#10;  
     encoder_in=16'b1000010011000100;#10;
     
     $finish;

end
endmodule

//iverilog -o encoder16to4_tb.vvp encoder16to4_tb.v
//vvp encoder16to4_tb.vvp

Encoder/encoder16to4_tb.vcd
$date
	Fri Jul 15 07:05:23 2022
$end
$version
	Icarus Verilog
$end
$timescale
	1s
$end
$scope module encoder16to4_tb $end
$var wire 1 ! valid $end
$var wire 4 " encoder_out [3:0] $end
$var reg 16 # encoder_in [15:0] $end
$scope module iencoder16to4 $end
$var wire 16 $ encoder_in [15:0] $end
$var reg 4 % encoder_out [3:0] $end
$var reg 1 ! valid $end
$upscope $end
$upscope $end
$enddefinitions $end
#0
$dumpvars
b0 %
b0 $
b0 #
b0 "
0!
$end
#10
1!
b1 #
b1 $
#20
b1 "
b1 %
b10 #
b10 $
#30
b10 "
b10 %
b100 #
b100 $
#40
b11 "
b11 %
b1000 #
b1000 $
#50
b100 "
b100 %
b10000 #
b10000 $
#60
b1111 "
b1111 %
b1000000000000000 #
b1000000000000000 $
#70
b0 "
b0 %
0!
b1000010001000000 #
b1000010001000000 $
#80
b1000010001000100 #
b1000010001000100 $
#90
b1000010011000100 #
b1000010011000100 $
