Counter/upCounter.v
module upCounter(clk,resetCounter,count_in,count_out);

input clk;
input resetCounter;
input count_in;
output reg [9:0]count_out;
 
always @ (posedge clk) begin
 if (resetCounter)
  count_out <= 0;
 else if (count_in)
  count_out <= count_out + 1;
end   

endmodule

Counter/upCounter_tb.v
`include "upCounter.v"

module upCounter_tb;
reg  clk, resetCounter,count_in;
wire [9:0]count_out;

upCounter iupCounter(.*);

initial begin
    clk=0;
    forever #5 clk=~clk;
end

initial begin
    $monitor("Time=%2d, Clock=%b, Reset=%b, count=%b \n",$time,clk,resetCounter,count_out);
    $dumpfile("upCounter_tb.vcd");
    $dumpvars(0, upCounter_tb);
    
    resetCounter=0;
    count_in=0;
    #10;

    resetCounter=1;
    #10;
    resetCounter=0;
    #10;
    count_in=1;
    #10;
    count_in=0;
    #10;
    count_in=1;
    #10;
    count_in=0;
    #10;
    count_in=1;
    #10;
    count_in=0;

    #50
    $finish;

end
endmodule

//iverilog -o upCounter_tb.vvp upCounter_tb.v
//vvp upCounter_tb.vvp
//gtkwave

Counter/upCounter_tb.vcd
$date
	Fri Jul 15 07:24:49 2022
$end
$version
	Icarus Verilog
$end
$timescale
	1s
$end
$scope module upCounter_tb $end
$var wire 10 ! count_out [9:0] $end
$var reg 1 " clk $end
$var reg 1 # count_in $end
$var reg 1 $ resetCounter $end
$scope module iupCounter $end
$var wire 1 " clk $end
$var wire 1 # count_in $end
$var wire 1 $ resetCounter $end
$var reg 10 % count_out [9:0] $end
$upscope $end
$upscope $end
$enddefinitions $end
#0
$dumpvars
bx %
0$
0#
0"
bx !
$end
#5
1"
#10
0"
1$
#15
b0 !
b0 %
1"
#20
0"
0$
#25
1"
#30
0"
1#
#35
b1 !
b1 %
1"
#40
0"
0#
#45
1"
#50
0"
1#
#55
b10 !
b10 %
1"
#60
0"
0#
#65
1"
#70
0"
1#
#75
b11 !
b11 %
1"
#80
0"
0#
