Register (PIPO)/PIPO.v

module PIPO (clk,reset,pipo_in,load,pipo_out);

input clk;
input reset;
input [3:0] pipo_in;
input load;
output reg [3:0] pipo_out;


always @(posedge clk)
begin
    if (reset)
    begin
        pipo_out <= 4'b0000;
    end
    else if (load)
    begin
        pipo_out <= pipo_in;
    end
end

endmodule

Register (PIPO)/PIPO_tb.v
`include "PIPO.v"

module PIPO_tb;

    reg clk;
    reg reset;
    reg  [3:0]pipo_in;
    reg load;
    wire [3:0]pipo_out;
    
    PIPO iPIPO (.*);   

    initial begin
    clk=0;
    forever
    #5 clk= ~clk;
    end 
    
    initial begin
        $monitor("Reset=%b Input=%b, load=%b output=%b",reset,pipo_in,load,pipo_out);
        $dumpfile("PIPO_tb.vcd");
        $dumpvars(0, PIPO_tb);

        reset=0; pipo_in =0;load=0;#20;
       
        #10;reset=0; pipo_in =4'b1001;load=1;
        #10;reset=0; pipo_in =4'b1011;load=0;
        #10;reset=0; load=1;
        #10;reset=0; pipo_in =4'b0001;load=1;
        #10;reset=0; pipo_in =4'b1111;load=1;
        #10;reset=0; pipo_in =4'b1010;load=0;
        #10;reset=0; load=1;
        

        #200;
        $finish;
    end
    
    //iverilog -o PIPO_tb.vvp PIPO_tb.v
    //vvp PIPO_tb.vvp
    //gtkwave

endmodule

Register (PIPO)/PIPO_tb.vcd
$date
	Fri Jul 15 07:14:19 2022
$end
$version
	Icarus Verilog
$end
$timescale
	1s
$end
$scope module PIPO_tb $end
$var wire 4 ! pipo_out [3:0] $end
$var reg 1 " clk $end
$var reg 1 # load $end
$var reg 4 $ pipo_in [3:0] $end
$var reg 1 % reset $end
$scope module iPIPO $end
$var wire 1 " clk $end
$var wire 1 # load $end
$var wire 4 & pipo_in [3:0] $end
$var wire 1 % reset $end
$var reg 4 ' pipo_out [3:0] $end
$upscope $end
$upscope $end
$enddefinitions $end
#0
$dumpvars
bx '
b0 &
0%
b0 $
0#
0"
bx !
$end
#5
1"
#10
0"
#15
1"
#20
0"
#25
1"
#30
0"
1#
b1001 $
b1001 &
#35
b1001 !
b1001 '
1"
#40
0"
0#
b1011 $
b1011 &
#45
1"
#50
0"
1#
#55
b1011 !
b1011 '
1"
#60
0"
b1 $
b1 &
#65
b1 !
b1 '
1"
#70
0"
b1111 $
b1111 &
#75
b1111 !
b1111 '
1"
#80
0"
0#
b1010 $
b1010 &
#85
1"
#90
0"
1#
#95
b1010 !
b1010 '
1"
